[
  {
    "text": "Trending GitHub repo: Leantime/leantime",
    "source": "GitHub",
    "url": "https://github.com/Leantime/leantime",
    "category": "Open Source",
    "cleaned_text": "trending github repo leantimeleantime"
  },
  {
    "text": "Trending GitHub repo: microsoft/presidio",
    "source": "GitHub",
    "url": "https://github.com/microsoft/presidio",
    "category": "Open Source",
    "cleaned_text": "trending github repo microsoftpresidio"
  },
  {
    "text": "Trending GitHub repo: aquasecurity/trivy",
    "source": "GitHub",
    "url": "https://github.com/aquasecurity/trivy",
    "category": "Open Source",
    "cleaned_text": "trending github repo aquasecuritytrivy"
  },
  {
    "text": "Trending GitHub repo: bitwarden/clients",
    "source": "GitHub",
    "url": "https://github.com/bitwarden/clients",
    "category": "Open Source",
    "cleaned_text": "trending github repo bitwardenclients"
  },
  {
    "text": "Trending GitHub repo: carbon-design-system/carbon",
    "source": "GitHub",
    "url": "https://github.com/carbon-design-system/carbon",
    "category": "Open Source",
    "cleaned_text": "trending github repo carbondesignsystemcarbon"
  },
  {
    "text": "Trending GitHub repo: apache/arrow",
    "source": "GitHub",
    "url": "https://github.com/apache/arrow",
    "category": "Open Source",
    "cleaned_text": "trending github repo apachearrow"
  },
  {
    "text": "Trending GitHub repo: makeplane/plane",
    "source": "GitHub",
    "url": "https://github.com/makeplane/plane",
    "category": "Open Source",
    "cleaned_text": "trending github repo makeplaneplane"
  },
  {
    "text": "Trending GitHub repo: rothgar/awesome-tuis",
    "source": "GitHub",
    "url": "https://github.com/rothgar/awesome-tuis",
    "category": "Open Source",
    "cleaned_text": "trending github repo rothgarawesometuis"
  },
  {
    "text": "Trending GitHub repo: wagtail/wagtail",
    "source": "GitHub",
    "url": "https://github.com/wagtail/wagtail",
    "category": "Open Source",
    "cleaned_text": "trending github repo wagtailwagtail"
  },
  {
    "text": "Trending GitHub repo: googleapis/release-please-action",
    "source": "GitHub",
    "url": "https://github.com/googleapis/release-please-action",
    "category": "Open Source",
    "cleaned_text": "trending github repo googleapisreleasepleaseaction"
  }
]